
{"items":[{"name":"Introduction","href":"index.html","topicHref":"index.html"},{"name":"User Guide","href":"user/USER_GUIDE.html","tocHref":"user/toc.html","topicHref":"user/USER_GUIDE.html"},{"name":"API Reference","includedFrom":"~/obj/api/toc.yml","items":[{"name":"PlcComm.Toyopuc","topicUid":"PlcComm.Toyopuc","type":"Namespace","items":[{"name":"ClockData","topicUid":"PlcComm.Toyopuc.ClockData","type":"Class"},{"name":"CpuStatusData","topicUid":"PlcComm.Toyopuc.CpuStatusData","type":"Class"},{"name":"ExNoAddress32","topicUid":"PlcComm.Toyopuc.ExNoAddress32","type":"Class"},{"name":"ExtNoAddress","topicUid":"PlcComm.Toyopuc.ExtNoAddress","type":"Class"},{"name":"ParsedAddress","topicUid":"PlcComm.Toyopuc.ParsedAddress","type":"Class"},{"name":"RelayLayer","topicUid":"PlcComm.Toyopuc.RelayLayer","type":"Class"},{"name":"ResolvedDevice","topicUid":"PlcComm.Toyopuc.ResolvedDevice","type":"Class"},{"name":"ResponseFrame","topicUid":"PlcComm.Toyopuc.ResponseFrame","type":"Class"},{"name":"ToyopucAddress","topicUid":"PlcComm.Toyopuc.ToyopucAddress","type":"Class"},{"name":"ToyopucAddressRange","topicUid":"PlcComm.Toyopuc.ToyopucAddressRange","type":"Class"},{"name":"ToyopucAddressingOptions","topicUid":"PlcComm.Toyopuc.ToyopucAddressingOptions","type":"Class"},{"name":"ToyopucAreaDescriptor","topicUid":"PlcComm.Toyopuc.ToyopucAreaDescriptor","type":"Class"},{"name":"ToyopucClient","topicUid":"PlcComm.Toyopuc.ToyopucClient","type":"Class"},{"name":"ToyopucDeviceCatalog","topicUid":"PlcComm.Toyopuc.ToyopucDeviceCatalog","type":"Class"},{"name":"ToyopucDeviceClient","topicUid":"PlcComm.Toyopuc.ToyopucDeviceClient","type":"Class"},{"name":"ToyopucDeviceClientExtensions","topicUid":"PlcComm.Toyopuc.ToyopucDeviceClientExtensions","type":"Class"},{"name":"ToyopucDeviceProfile","topicUid":"PlcComm.Toyopuc.ToyopucDeviceProfile","type":"Class"},{"name":"ToyopucDeviceProfiles","topicUid":"PlcComm.Toyopuc.ToyopucDeviceProfiles","type":"Class"},{"name":"ToyopucDeviceResolver","topicUid":"PlcComm.Toyopuc.ToyopucDeviceResolver","type":"Class"},{"name":"ToyopucError","topicUid":"PlcComm.Toyopuc.ToyopucError","type":"Class"},{"name":"ToyopucProtocol","topicUid":"PlcComm.Toyopuc.ToyopucProtocol","type":"Class"},{"name":"ToyopucProtocolError","topicUid":"PlcComm.Toyopuc.ToyopucProtocolError","type":"Class"},{"name":"ToyopucRelay","topicUid":"PlcComm.Toyopuc.ToyopucRelay","type":"Class"},{"name":"ToyopucTimeoutError","topicUid":"PlcComm.Toyopuc.ToyopucTimeoutError","type":"Class"},{"name":"ToyopucTraceDirection","topicUid":"PlcComm.Toyopuc.ToyopucTraceDirection","type":"Enum"},{"name":"ToyopucTraceFrame","topicUid":"PlcComm.Toyopuc.ToyopucTraceFrame","type":"Class"},{"name":"ToyopucTransportMode","topicUid":"PlcComm.Toyopuc.ToyopucTransportMode","type":"Enum"},{"name":"TransportTraceFrame","topicUid":"PlcComm.Toyopuc.TransportTraceFrame","type":"Class"}]}]}]}
